{"inkVersion":21,"root":[[{"->":"section1"},["done",{"#f":5,"#n":"g-0"}],null],"done",{"section1":[["#","^background Rivendell","/#","#","^mood neutral","/#","#","^speaker -","/#","^In the lush valley of Imladris, it came to pass that the free folks gathered in an arrangement of chairs for Elrond's council.","\n","#","^speaker Elrond","/#","^Far have you travelled, wanderers from distant lands, to be seated now in these very chairs of mine.","\n","^We shall now discuss the matter of The One, the MASTER ring smithied by Sauron, the one item he seeks so dearly.","\n","^We must decide now, how to prevent him from getting it.","\n","#","^speaker Gimli","/#","^Then why shan't I shatter The Ring right now?","\n","#","^speaker -","/#","^And Gimli arose from his chair, took a swing and smote his axe upon The Ring. But alas, it didn't took a scratch and everyone was a little sad.","\n","ev","str","^airhorn","/str","/ev",{"*":".^.c-0","flg":4},"ev","str","^sadduck","/str","/ev",{"*":".^.c-1","flg":4},"ev","str","^cicarda","/str","/ev",{"*":".^.c-2","flg":4},"ev","str","^badumtss","/str","/ev",{"*":".^.c-3","flg":4},"ev","str","^dundunndunnn","/str","/ev",{"*":".^.c-4","flg":4},"ev","str","^catcallwhistle","/str","/ev",{"*":".^.c-5","flg":4},"ev","str","^angryboat","/str","/ev",{"*":".^.c-6","flg":4},"ev","str","^awwww","/str","/ev",{"*":".^.c-7","flg":4},"ev","str","^clap","/str","/ev",{"*":".^.c-8","flg":4},{"c-0":["^      \t",{"->":"airhorn1"},"\n",{"#f":5}],"c-1":["^      \t",{"->":"sadduck1"},"\n",{"#f":5}],"c-2":["^      \t",{"->":"cicarda1"},"\n",{"#f":5}],"c-3":["^     \t",{"->":"badumtss1"},"\n",{"#f":5}],"c-4":["^ \t",{"->":"dundunndunnn1"},"\n",{"#f":5}],"c-5":["^  ",{"->":"catcallwhistle1"},"\n",{"#f":5}],"c-6":["^     \t",{"->":"angryboat1"},"\n",{"#f":5}],"c-7":["^     \t\t",{"->":"awwww1"},"\n",{"#f":5}],"c-8":["^     \t\t",{"->":"clap1"},"\n",{"#f":5}]}],{"#f":1}],"airhorn1":["#","^speaker Gimli","/#","#","^mood neutral","/#","^Oh why! Yes, my action should indeed be repeated!","\n","#","^speaker -","/#","^And while the other council members shook their heads and judged Gimli, the young dwarf confidently walked up to The Ring.","\n","^... and SHATTERED it, thus destroying Sauron and saving the West.","\n","done",{"#f":1}],"sadduck1":[{"->":"section2"},{"#f":1}],"cicarda1":["#","^speaker -","/#","^The absence of any yet so quiet sound brought the council members nerves on edge, and they all needed a thorough spa session in Elrond's extensive hall of hot ponds.","\n","^Four hours later...","\n",{"->":"section2"},{"#f":1}],"badumtss1":["#","^speaker -","/#","^As the council broke away in laughter, sinking with endless streams of tears in their eyes to the ground, Gimli stood alone and sad.","\n",{"->":"section2"},{"#f":1}],"dundunndunnn1":["#","^speaker Elrond","/#","^Thus the great menace that this ring and Sauron are, is unveiled. Futile are the dwarfs efforts.","\n","#","^speaker Gandalf","/#","^Futile the efforts of many in this council would be, myself included.","\n","#","^speaker Boromir","/#","^Futile all of our efforts seem.","\n","#","^speaker -","/#","^When Arwen returned home, she found nothing but a collection of letters bidding farewell on the stone table where the council was held.","\n","^Long after would she be seen standing at the edge of the cliffs nearby, the river Bruinen deep below washing away memories.","\n","done",{"#f":1}],"catcallwhistle1":["#","^speaker -","/#","^Legolas was in awe of the dwarfs display of muscles.","\n",{"->":"section2"},{"#f":1}],"angryboat1":["#","^speaker Gimli","/#","#","^mood shook","/#","^Huh!!","\n","#","^speaker Elrond","/#","^What have.. you done?","\n","#","^speaker -","/#","^Blackness sank over the valley, and dark whispers echoed in Elrond's halls. The elves shook in fear.","\n","^Sauron descended from a dark shadow that had formed above the council chamber and stood before them: menacing, tall and terrible.","\n","^And then he pr- arrrgggghhh...","\n","done",{"#f":1}],"awwww1":["#","^speaker Gimli","/#","#","^mood shook","/#","^(mutters into his beard)","\n","#","^speaker Legolas","/#","^He's cute..","\n",{"->":"section2"},{"#f":1}],"clap1":[{"->":"section2"},"done",{"#f":1}],"section2":[["#","^speaker Gimli","/#","#","^mood shook","/#","^...","\n","#","^speaker Aragorn","/#","^Don't be ashamed Gimli, son of Glóin, for none here could have mustered the strength to carve a yet so little scar into the Dark Lords masterpiece.","\n","#","^speaker Gandalf","/#","^Aragorn speaks wisely. The Ring cannot be easily destroyed, at least not by us: not by the hot ovens under the Lonely Mountain -","\n","^I dare say not even the smoldering fires within the mightiest dragon of yore, Ancalagon the Black, could have molten The Ring.","\n","#","^speaker Legolas","/#","^But that is terrible news! We cannot hide it, for none of our holds will withstand Saurons test over time, we cannot defeat Sauron, for he is too powerful already, and now you say we cannot destroy it!","\n","^What hope is left, then?","\n","#","^speaker Gandalf","/#","^...","\n","#","^speaker Elrond","/#","^(sighs) There is one way to destroy it.","\n","^The Ring must be taken the long way to the dark lands of Mordor, carried over the plains of Gorgoroth and cast into the fires of Mount Doom, Orodruin, where it was crafted.","\n","^And it is one of you that must do this deed.","\n","ev","str","^airhorn","/str","/ev",{"*":".^.c-0","flg":4},"ev","str","^sadduck","/str","/ev",{"*":".^.c-1","flg":4},"ev","str","^cicarda","/str","/ev",{"*":".^.c-2","flg":4},"ev","str","^badumtss","/str","/ev",{"*":".^.c-3","flg":4},"ev","str","^dundunndunnn","/str","/ev",{"*":".^.c-4","flg":4},"ev","str","^catcallwhistle","/str","/ev",{"*":".^.c-5","flg":4},"ev","str","^angryboat","/str","/ev",{"*":".^.c-6","flg":4},"ev","str","^awwww","/str","/ev",{"*":".^.c-7","flg":4},"ev","str","^clap","/str","/ev",{"*":".^.c-8","flg":4},{"c-0":["^      \t",{"->":"airhorn2"},"\n",{"#f":5}],"c-1":["^      \t",{"->":"sadduck2"},"\n",{"#f":5}],"c-2":["^      \t",{"->":"cicarda2"},"\n",{"#f":5}],"c-3":["^     \t",{"->":"badumtss2"},"\n",{"#f":5}],"c-4":["^ \t",{"->":"dundunndunnn2"},"\n",{"#f":5}],"c-5":["^  ",{"->":"catcallwhistle2"},"\n",{"#f":5}],"c-6":["^     \t",{"->":"angryboat2"},"\n",{"#f":5}],"c-7":["^     \t\t",{"->":"awwww2"},"\n",{"#f":5}],"c-8":["^     \t\t",{"->":"clap2"},"\n",{"#f":5}]}],{"#f":1}],"airhorn2":["#","^speaker Elrond","/#","^Wohoo! I know it's exciting right?","\n",{"->":"section3"},{"#f":1}],"sadduck2":["#","^speaker Legolas","/#","^What grief! What grief! Ai oi!","\n",{"->":"section3"},{"#f":1}],"cicarda2":["#","^speaker Elrond","/#","^...","\n","#","^speaker Legolas","/#","^Oh I can't stand this silence!","\n",{"->":"section3"},{"#f":1}],"badumtss2":[{"->":"section3"},{"#f":1}],"dundunndunnn2":["#","^speaker Legolas","/#","^What grief! What grief! Ai oi!","\n",{"->":"section3"},{"#f":1}],"catcallwhistle2":[{"->":"section3"},{"#f":1}],"angryboat2":["#","^speaker Legolas","/#","^What grief! What grief! Ai oi!","\n",{"->":"section3"},{"#f":1}],"awwww2":["#","^speaker Legolas","/#","^What grief! What grief! Ai oi!","\n",{"->":"section3"},{"#f":1}],"clap2":["#","^speaker Gandalf","/#","^We're in a grave situation indeed.","\n",{"->":"section3"},{"#f":1}],"section3":[["#","^speaker Gimli","/#","#","^mood shook","/#","^...","\n","#","^speaker Frodo","/#","#","^mood shook","/#","^...","\n","#","^speaker Gandalf","/#","^...","\n","#","^speaker Frodo","/#","#","^mood neutral","/#","^..","\n","#","^speaker Gandalf","/#","^..!","\n","#","^speaker Frodo","/#","#","^mood neutral","/#","^I will do it. I will carry the Ring to Mordor! Though I do not know the way..","\n","ev","str","^airhorn","/str","/ev",{"*":".^.c-0","flg":4},"ev","str","^sadduck","/str","/ev",{"*":".^.c-1","flg":4},"ev","str","^cicarda","/str","/ev",{"*":".^.c-2","flg":4},"ev","str","^badumtss","/str","/ev",{"*":".^.c-3","flg":4},"ev","str","^dundunndunnn","/str","/ev",{"*":".^.c-4","flg":4},"ev","str","^catcallwhistle","/str","/ev",{"*":".^.c-5","flg":4},"ev","str","^angryboat","/str","/ev",{"*":".^.c-6","flg":4},"ev","str","^awwww","/str","/ev",{"*":".^.c-7","flg":4},"ev","str","^clap","/str","/ev",{"*":".^.c-8","flg":4},{"c-0":["^      \t",{"->":"airhorn3"},"\n",{"#f":5}],"c-1":["^      \t",{"->":"sadduck3"},"\n",{"#f":5}],"c-2":["^      \t",{"->":"cicarda3"},"\n",{"#f":5}],"c-3":["^     \t",{"->":"badumtss3"},"\n",{"#f":5}],"c-4":["^ \t",{"->":"dundunndunnn3"},"\n",{"#f":5}],"c-5":["^  ",{"->":"catcallwhistle3"},"\n",{"#f":5}],"c-6":["^     \t",{"->":"angryboat3"},"\n",{"#f":5}],"c-7":["^     \t\t",{"->":"awwww3"},"\n",{"#f":5}],"c-8":["^     \t\t",{"->":"clap3"},"\n",{"#f":5}]}],{"#f":1}],"airhorn3":["#","^speaker Frodo","/#","#","^mood neutral","/#","^Anyway LET! US! GO! I am READY for this journey, Sam let's grab that ring and hike yonder!","\n","#","^speaker -","/#","^It was then that Gandalf and Elrond realized they had made a grand mistake trusting in a hobbit, the most party-adjacent of all creatures.","\n","done",{"#f":1}],"sadduck3":["#","^speaker Frodo","/#","#","^mood shook","/#","^...","\n","#","^speaker -","/#","^Frodo's heart sank as everyone looked at him with grave pity and disbelief. Not even Gandalf trusted him with this task.","\n","^He clearly overstepped a line, so he sat down again and stayed silent from now on.","\n","^The ring was eventually entrusted to a no-name elf from Elrond's house hold, who gathered a much smaller fellowship than Frodo would have and fell to the rings ensnaring soon thereafter.","\n","done",{"#f":1}],"cicarda3":["#","^speaker -","/#","^In the glaring silence only the rustling autumnal leaves of Imladris trees could be heard, and faint songs of elves in the distance. But suddenly-","\n","#","^speaker Sam","/#","^Wait! Mr. Frodo I couldn't leave you alone in such perils! I will come with you!","\n","#","^speaker Elrond","/#","^Indeed, as it seems that not even the non-invitation to a secret council can discourage you from holding to your friend. So be it.","\n","#","^speaker Elrond","/#","^You are brave, Frodo, Drogos son. And we won't send you on this journey all alone and without help. The free folks shall each send a companion with you.","\n","#","^speaker Aragorn","/#","^Wherever you go, I will help you as best as I may, I'll follow you, and be it until the very doorstep of Sammath Naur where the Ring first saw the Earth. You have my sword.","\n","#","^speaker Legolas","/#","^And you have my bow!","\n","#","^speaker Gimli","/#","#","^mood neutral","/#","^And my axe!","\n","#","^speaker Sam","/#","^And my pan!","\n","#","^speaker -","/#","^When everyone had proclaimed there respective weaponry at hand, the fellowship had formed: the FELLOWSHIP of the RING. Much peril would they endure in the times to come.","\n","done",{"#f":1}],"badumtss3":["#","^speaker -","/#","^It was hard for Elrond to not break into laughter. He really tried not to. But amidst the storm of giggles and open joy at the expense of the poor hobbit, the old Elfs barriers at last fell.","\n","#","^speaker Gandalf","/#","^Y- You..!! (lul)","\n","#","^speaker -","/#","^Gandalf was in tears for he had never witnessed a joke so wonderful and absurd.","\n","^For many years he would tell the story of Frodo the Funny to enlighten the hearts of man, elf and every free creature under the western sun.","\n","done",{"#f":1}],"dundunndunnn3":["#","^speaker -","/#","^The council sat in silence, pondering the heavy burden the young hobbit had just laid upon himself, and everyone felt a little ashamed they hadn't come forth themselves.","\n","#","^speaker Elrond","/#","^I saw this to be a future path from here on. You are brave, Frodo, Drogos son. And we won't send you on this journey all alone and without help. The free folks shall each send a companion with you.","\n","#","^speaker Frodo","/#","#","^mood shook","/#","^...","\n","#","^speaker Aragorn","/#","^Wherever you go, I will help you as best as I may, I'll follow you, and be it until the very doorstep of Sammath Naur where the Ring first saw the Earth. You have my sword.","\n","#","^speaker Legolas","/#","^And you have my bow!","\n","#","^speaker Gimli","/#","#","^mood neutral","/#","^And my axe!","\n","#","^speaker Sam","/#","^And my pan!","\n","#","^speaker -","/#","^When everyone had proclaimed there respective weaponry at hand, the fellowship had formed: the FELLOWSHIP of the RING. Much peril would they endure in the times to come.","\n","done",{"#f":1}],"catcallwhistle3":["#","^speaker -","/#","^Gimli and Legolas had exchanged meaningful glances, a romantic tension was in the air.","\n","#","^speaker Frodo","/#","#","^mood shook","/#","^...","\n","#","^speaker Gandalf","/#","^Let's give those two some space and continue the meeting another day.","\n","#","^speaker -","/#","^The council, indeed, didn't continue the meeting another day, but procastinated the decision instead until Sauron stood on Rivendell's doorstop.","\n","^After a brutal siege Elrond's hold fell, and once more darkness reigned in all of Middle-Earth.","\n","done",{"#f":1}],"angryboat3":["#","^speaker Gimli","/#","#","^mood shook","/#","^It seems to me as if the Dark Lord had called from far away, responding to our challenge.","\n","#","^speaker Elrond","/#","^Sauron is mighty and far-reaching already.","\n","#","^speaker Boromir","/#","^He is powerful indeed, and his wild forces have taken so much of the once glorious realm of Gondor already. He is standing before our doorstep and soon will invade Rohan and then Eriador.","\n","#","^speaker -","/#","^Five hours of doomspeak later, Frodo was devoid of any strength and stared flatly into the nightsky.","\n","^Forever.","\n","done",{"#f":1}],"awwww3":["#","^speaker Gimli","/#","#","^mood neutral","/#","^What a sturdy hobbit here among us, and what courage!","\n","#","^speaker Legolas","/#","^A realm charm! Oh what I'd give to travel with such lovely fellows!","\n","#","^speaker Gandalf","/#","^A FELLOWSHIP! That is THE idea, you're a genius dear!","\n","#","^speaker Elrond","/#","^You are brave and cute, Frodo, Drogos son. It is indeed a fabulous idea to not send you on this journey all alone and without help. The free folks shall each send a companion with you!","\n","#","^speaker Aragorn","/#","^Wherever you go, I will help you as best as I may, I'll consider you lovely, and be it at the very doorstep of Sammath Naur where the Ring first saw the Earth. You have my sword.","\n","#","^speaker Legolas","/#","^And you have my bow!","\n","#","^speaker Gimli","/#","#","^mood neutral","/#","^And my axe!","\n","#","^speaker Sam","/#","^And my pan!","\n","#","^speaker -","/#","^When everyone had proclaimed there respective weaponry at hand, the fellowship had formed: the FELLOWSHIP of the RING. Much peril would they endure in the times to come.","\n","done",{"#f":1}],"clap3":["#","^speaker Frodo","/#","#","^mood shook","/#","^Oh thank you, high council of Elrond! I am moved to tears and will be particular solemn and melancholic on this journey, as I never would've been elsewise!","\n","#","^speaker -","/#","^The council is shaken by the thought, but none dares speaking what they think.","\n","^An awkward silence is spreading.","\n","#","^speaker Boromir","/#","^Will no one stand by this brave halfling? Frodo, little do I know you or your kind, but I now know that my sword will be by your side, even if none else will follow.","\n","#","^speaker -","/#","^And since indeed no one could bear the thought of seeing Frodo's ultra sad face all day long for many months, Boromir and Frodo left Rivendell alone and had a heartfelt bromance.","\n","^Until Boromir strangled Frodo and forced him to pass over the ring, leading the lands east of the Great Sea into a second darkness.","\n","done",{"#f":1}],"#f":1}],"listDefs":{}}